{
  "display": {
    "icon": {
      "id": "minecraft:oak_sapling"
    },
		"frame": "goal",
    "title": "It's Oakay Now",
    "description": "Buy some oak or dark oak saplings from a wandering trader"
  },
  "parent": "sbp:skyblock/green_deal",
  "criteria": {
    "minecraft:oak_sapling": {
      "trigger": "minecraft:inventory_changed",
      "conditions": {
        "items": [
          {
            "items": "minecraft:oak_sapling"
          }
        ]
      }
    },
		"minecraft:dark_oak_sapling": {
      "trigger": "minecraft:inventory_changed",
      "conditions": {
        "items": [
          {
            "items": "minecraft:dark_oak_sapling"
          }
        ]
      }
    }
  },
  "requirements": [
    [
      "minecraft:oak_sapling",
			"minecraft:dark_oak_sapling"
    ]
  ]
}
